Guia 6/Guia1/11_aluDeco.v
module aluDeco(
    input wire op5,f7,
    input wire [1:0] aluOp,
    input wire [2:0] f3,
    output reg [2:0] aluControl
);

always @(*)
begin
    case (aluOp)
    2'b00: begin
        aluControl <= 3'b000;
    end

    2'b01: begin
        aluControl <= 3'b001;
    end

    2'b10: begin
        case (f3)
            3'b000: begin
                if (op5 == 1 && f7 == 1)
                    aluControl <= 3'b001;
                else aluControl <= 3'b000;
            end

            3'b010: aluControl <= 3'b101;

            3'b110: aluControl <= 3'b011;

            3'b111: aluControl <= 3'b010;
        endcase
    end

    endcase
end

endmodule

Guia 6/Guia1/09_UC_tb.v
`default_nettype none
`define DUMPSTR(x) `"x.vcd`"
`timescale 100 ns / 10 ns

module UC_09_tb();

parameter DURATION = 10;
reg clk = 0;
always #0.5 clk = ~clk;

reg op5, f7;
reg [1:0] aluOp;
reg [2:0] f3;
wire [2:0] aluControl;

aluDeco aluDeco_1 (
    .op5(op5),
    .f7(f7),
    .aluOp(aluOp),
    .f3(f3),
    .aluControl(aluControl)
);

initial begin
    $dumpfile(`DUMPSTR(`VCD_OUTPUT));
    $dumpvars(0, UC_09_tb);

    #1
    aluOp = 2'b00;

    #3
    aluOp = 2'b01;

    #3
    aluOp = 2'b10;
    f3 = 3'b000;
    op5 = 1'b0;
    f7 = 1'b0;

    #3
    f3 = 3'b000;
    op5 = 1'b1;
    f7 = 1'b1;

    #3
    f3 = 3'b010;

    #3
    f3 = 3'b110;

    #3
    f3 = 3'b111;

    #(DURATION) $display("End of simulation");
    $finish;
end

endmodule

Guia 6/OrgComp/Procesador/03_BR.v
module BR(
    input wire clk, we,
    input wire [4:0] a1, a2, a3, 
    input wire [31:0] wd3,
    output wire [31:0] rd1, rd2
);

reg [31:0] banco [31:0];

always @(posedge clk) begin
    if (we) begin
        banco[a3] <= wd3;
    end
end

assign rd1 = (a1 != 0) ? banco[a1] : 1'b0;
assign rd2 = (a2 != 0) ? banco[a2] : 1'b0;

endmodule

Guia 6/Guia1/02_IM.v
module IM(
    input wire [15:0] adress,
    output wire [31:0] rd
);
reg [31:0] memoria [63:0];

assign rd = memoria[adress];
endmodule

Guia 6/OrgComp/Procesador/01_PC.v
module PC(
    input wire clk,
    input wire [15:0] pcNext,
    output reg [15:0] pc
);

always @(posedge clk)
    begin
        pc <= pcNext;
    end
endmodule

Guia 6/Guia1/Ej_01_tb.v
`default_nettype none
`define DUMPSTR(x) `"x.vcd`"
`timescale 100 ns / 10 ns

module Ej_01_tb();

parameter DURATION = 10;
reg clk = 0;
always #0.5 clk = ~clk;

reg [15:0] test_pcNext;
wire [15:0] test_pc;
PC PC_1 (
    .clk(clk),
    .pcNext(test_pcNext),
    .pc(test_pc)
);

reg [15:0] test_adress;
wire [31:0] test_rd;
IM IM_1(
    .adress(test_adress),
    .rd(test_rd)
);

reg test_we;
reg [4:0] test_a1, test_a2, test_a3;
reg [31:0] test_wd3;
wire [31:0] test_rd1, test_rd2;
BR BR_1(
    .clk(clk),
    .we(test_we),
    .a1(test_a1),
    .a2(test_a2),
    .a3(test_a3),
    .wd3(test_wd3),
    .rd1(test_rd1),
    .rd2(test_rd2)
);

initial begin
    $dumpfile(`DUMPSTR(`VCD_OUTPUT));
    $dumpvars(0, Ej_01_tb);

    test_we = 1;
    test_a1 = 0;
    test_a2 = 1;
    test_a3 = 0;
    test_wd3 = 0;
    
    #1
    test_pcNext = 0;
    test_adress = 0;

    test_a3 = 1;
    test_wd3 = 1;

    #5
    test_pcNext = 1;
    test_adress = 1;

    test_a3 = 2;
    test_wd3 = 2;

    #5
    test_pcNext = 2;
    test_adress = 2;

    test_we = 0;


    #5
    test_pcNext = 3;
    test_adress = 3;

    test_a1 = 2;
    test_a2 = 3;

    #(DURATION) $display("End of simulation");
    $finish;
end

endmodule

Guia 6/Guia1/09_UC_tb.vcd
$date
	Tue Oct 10 10:19:55 2023
$end
$version
	Icarus Verilog
$end
$timescale
	1ps
$end
$scope module Ej_01_tb $end
$var wire 32 ! test_rd2 [31:0] $end
$var wire 32 " test_rd1 [31:0] $end
$var wire 32 # test_rd [31:0] $end
$var wire 16 $ test_pc [15:0] $end
$var reg 1 % clk $end
$var reg 5 & test_a1 [4:0] $end
$var reg 5 ' test_a2 [4:0] $end
$var reg 5 ( test_a3 [4:0] $end
$var reg 16 ) test_adress [15:0] $end
$var reg 16 * test_pcNext [15:0] $end
$var reg 32 + test_wd3 [31:0] $end
$var reg 1 , test_we $end
$scope module BR_1 $end
$var wire 5 - a1 [4:0] $end
$var wire 5 . a2 [4:0] $end
$var wire 5 / a3 [4:0] $end
$var wire 1 % clk $end
$var wire 32 0 wd3 [31:0] $end
$var wire 1 , we $end
$var wire 32 1 rd2 [31:0] $end
$var wire 32 2 rd1 [31:0] $end
$upscope $end
$scope module IM_1 $end
$var wire 16 3 adress [15:0] $end
$var wire 32 4 rd [31:0] $end
$upscope $end
$scope module PC_1 $end
$var wire 1 % clk $end
$var wire 16 5 pcNext [15:0] $end
$var reg 16 6 pc [15:0] $end
$upscope $end
$upscope $end
$scope module UC_09_tb $end
$var wire 3 7 aluControl [2:0] $end
$var reg 2 8 aluOp [1:0] $end
$var reg 1 9 clk $end
$var reg 3 : f3 [2:0] $end
$var reg 1 ; f7 $end
$var reg 1 < op5 $end
$scope module aluDeco_1 $end
$var wire 2 = aluOp [1:0] $end
$var wire 3 > f3 [2:0] $end
$var wire 1 ; f7 $end
$var wire 1 < op5 $end
$var reg 3 ? aluControl [2:0] $end
$upscope $end
$upscope $end
$enddefinitions $end
#0
$dumpvars
bx ?
bx >
bx =
x<
x;
bx :
09
bx 8
bx 7
bx 6
bx 5
bx 4
bx 3
b0 2
bx 1
b0 0
b0 /
b1 .
b0 -
1,
b0 +
bx *
bx )
b0 (
b1 '
b0 &
0%
bx $
bx #
b0 "
bx !
$end
#50000
19
1%
#100000
b0 7
b0 ?
09
0%
b0 8
b0 =
b1 +
b1 0
b1 (
b1 /
b0 )
b0 3
b0 *
b0 5
#150000
b1 !
b1 1
b0 $
b0 6
19
1%
#200000
09
0%
#250000
19
1%
#300000
09
0%
#350000
19
1%
#400000
b1 7
b1 ?
09
0%
b1 8
b1 =
#450000
19
1%
#500000
09
0%
#550000
19
1%
#600000
09
0%
b10 +
b10 0
b10 (
b10 /
b1 )
b1 3
b1 *
b1 5
#650000
b1 $
b1 6
19
1%
#700000
b0 7
b0 ?
09
0%
0;
0<
b0 :
b0 >
b10 8
b10 =
#750000
19
1%
#800000
09
0%
#850000
19
1%
#900000
09
0%
#950000
19
1%
#1000000
b1 7
b1 ?
09
0%
1;
1<
#1050000
19
1%
#1100000
09
0%
0,
b10 )
b10 3
b10 *
b10 5
#1150000
b10 $
b10 6
19
1%
#1200000
09
0%
#1250000
19
1%
#1300000
b101 7
b101 ?
09
0%
b10 :
b10 >
#1350000
19
1%
#1400000
09
0%
#1450000
19
1%
#1500000
09
0%
#1550000
19
1%
#1600000
b11 7
b11 ?
bx !
bx 1
b10 "
b10 2
09
0%
b110 :
b110 >
b11 '
b11 .
b10 &
b10 -
b11 )
b11 3
b11 *
b11 5
#1650000
b11 $
b11 6
19
1%
#1700000
09
0%
#1750000
19
1%
#1800000
09
0%
#1850000
19
1%
#1900000
b10 7
b10 ?
09
0%
b111 :
b111 >
