Guia 6/OrgComp/Procesador/03_BR.v
module BR(
    input wire clk, we,
    input wire [4:0] a1, a2, a3, 
    input wire [31:0] wd3,
    output wire [31:0] rd1, rd2
);

reg [31:0] banco [31:0];

always @(posedge clk) begin
    if (we) begin
        banco[a3] <= wd3;
    end
end

assign rd1 = (a1 != 0) ? banco[a1] : 1'b0;
assign rd2 = (a2 != 0) ? banco[a2] : 1'b0;

endmodule

Guia 6/Guia1/02_IM.v
module IM(
    input wire [15:0] adress,
    output wire [31:0] rd
);
reg [31:0] memoria [63:0];

assign rd = memoria[adress];
endmodule

Guia 6/OrgComp/Procesador/01_PC.v
module PC(
    input wire clk,
    input wire [15:0] pcNext,
    output reg [15:0] pc
);

always @(posedge clk)
    begin
        pc <= pcNext;
    end
endmodule

Guia 6/Guia1/Ej_01_tb.v
`default_nettype none
`define DUMPSTR(x) `"x.vcd`"
`timescale 100 ns / 10 ns

module Ej_01_tb();

parameter DURATION = 10;
reg clk = 0;
always #0.5 clk = ~clk;

reg [15:0] test_pcNext;
wire [15:0] test_pc;
PC PC_1 (
    .clk(clk),
    .pcNext(test_pcNext),
    .pc(test_pc)
);

reg [15:0] test_adress;
wire [31:0] test_rd;
IM IM_1(
    .adress(test_adress),
    .rd(test_rd)
);

reg test_we;
reg [4:0] test_a1, test_a2, test_a3;
reg [31:0] test_wd3;
wire [31:0] test_rd1, test_rd2;
BR BR_1(
    .clk(clk),
    .we(test_we),
    .a1(test_a1),
    .a2(test_a2),
    .a3(test_a3),
    .wd3(test_wd3),
    .rd1(test_rd1),
    .rd2(test_rd2)
);

initial begin
    $dumpfile(`DUMPSTR(`VCD_OUTPUT));
    $dumpvars(0, Ej_01_tb);

    test_we = 1;
    test_a1 = 0;
    test_a2 = 1;
    test_a3 = 0;
    test_wd3 = 0;
    
    #1
    test_pcNext = 0;
    test_adress = 0;

    test_a3 = 1;
    test_wd3 = 1;

    #5
    test_pcNext = 1;
    test_adress = 1;

    test_a3 = 2;
    test_wd3 = 2;

    #5
    test_pcNext = 2;
    test_adress = 2;

    test_we = 0;


    #5
    test_pcNext = 3;
    test_adress = 3;

    test_a1 = 2;
    test_a2 = 3;

    #(DURATION) $display("End of simulation");
    $finish;
end

endmodule

Guia 6/Guia1/Ej_01_tb.vcd
$date
	Tue Sep 19 11:37:48 2023
$end
$version
	Icarus Verilog
$end
$timescale
	1ps
$end
$scope module Ej_01_tb $end
$var wire 32 ! test_rd2 [31:0] $end
$var wire 32 " test_rd1 [31:0] $end
$var wire 32 # test_rd [31:0] $end
$var wire 16 $ test_pc [15:0] $end
$var reg 1 % clk $end
$var reg 5 & test_a1 [4:0] $end
$var reg 5 ' test_a2 [4:0] $end
$var reg 5 ( test_a3 [4:0] $end
$var reg 16 ) test_adress [15:0] $end
$var reg 16 * test_pcNext [15:0] $end
$var reg 32 + test_wd3 [31:0] $end
$var reg 1 , test_we $end
$scope module BR_1 $end
$var wire 5 - a1 [4:0] $end
$var wire 5 . a2 [4:0] $end
$var wire 5 / a3 [4:0] $end
$var wire 1 % clk $end
$var wire 32 0 wd3 [31:0] $end
$var wire 1 , we $end
$var reg 32 1 rd1 [31:0] $end
$var reg 32 2 rd2 [31:0] $end
$upscope $end
$scope module IM_1 $end
$var wire 16 3 adress [15:0] $end
$var wire 32 4 rd [31:0] $end
$upscope $end
$scope module PC_1 $end
$var wire 1 % clk $end
$var wire 16 5 pcNext [15:0] $end
$var reg 16 6 pc [15:0] $end
$upscope $end
$upscope $end
$enddefinitions $end
#0
$dumpvars
bx 6
bx 5
bx 4
bx 3
bx 2
bx 1
b0 0
b0 /
b1 .
b0 -
1,
b0 +
bx *
bx )
b0 (
b1 '
b0 &
0%
bx $
bx #
bx "
bx !
$end
#50000
1%
#100000
0%
b1 +
b1 0
b1 (
b1 /
b0 )
b0 3
b0 *
b0 5
#150000
b0 $
b0 6
1%
#200000
0%
#250000
1%
#300000
0%
#350000
1%
#400000
0%
#450000
1%
#500000
0%
#550000
1%
#600000
0%
b10 +
b10 0
b10 (
b10 /
b1 )
b1 3
b1 *
b1 5
#650000
b1 $
b1 6
1%
#700000
0%
#750000
1%
#800000
0%
#850000
1%
#900000
0%
#950000
1%
#1000000
0%
#1050000
1%
#1100000
0%
0,
b10 )
b10 3
b10 *
b10 5
#1150000
b1 !
b1 2
b0 "
b0 1
b10 $
b10 6
1%
#1200000
0%
#1250000
1%
#1300000
0%
#1350000
1%
#1400000
0%
#1450000
1%
#1500000
0%
#1550000
1%
#1600000
0%
b11 '
b11 .
b10 &
b10 -
b11 )
b11 3
b11 *
b11 5
#1650000
b11 $
b11 6
bx !
bx 2
b10 "
b10 1
1%
